ifm3dpy.cp310-win_amd64.pyd
ifm3dpy-1.6.12.dist-info/LICENSE
ifm3dpy-1.6.12.dist-info/LICENSE-thirdparty
ifm3dpy-1.6.12.dist-info/METADATA
ifm3dpy-1.6.12.dist-info/WHEEL
ifm3dpy-1.6.12.dist-info/entry_points.txt
ifm3dpy-1.6.12.dist-info/top_level.txt
ifm3dpy-1.6.12.dist-info/RECORD
