Metadata-Version: 2.4
Name: ifm3dpy
Version: 1.6.12
Summary: Library for working with ifm pmd-based 3D ToF Cameras
Home-page: https://github.com/ifm/ifm3d
Author: ifm Robotics Perception
Author-email: support.robotics@ifm.com
License: Apache 2.0
Project-URL: Documentation, https://ifm3d.com/
Project-URL: Issue Tracker, https://github.com/ifm/ifm3d/issues
Project-URL: Source Code, https://github.com/ifm/ifm3d
License-File: LICENSE
License-File: LICENSE-thirdparty
Requires-Dist: numpy
Dynamic: author
Dynamic: author-email
Dynamic: description
Dynamic: description-content-type
Dynamic: home-page
Dynamic: license
Dynamic: license-file
Dynamic: project-url
Dynamic: requires-dist
Dynamic: summary
